{
	"images":[
		{
			"title": "orewa luffy",
			"date":"5 April 2018",
			"path":"https://bangcodv.github.io/gambar/1.jpg"
		},

		{
			"title": "Raja bajak laut",
			"date":"6 April 2018",
			"path":"https://bangcodv.github.io/gambar/2.jpg"
		},
		{
			"title": "Luffy kecil",
			"date":"6 April 2018",
			"path":"https://bangcodv.github.io/gambar/3.jpg"
		},

		{
			"title": "Bendera Kami",
			"date":"7 April 2018",
			"path":"https://bangcodv.github.io/gambar/4.jpg"
		},
		{
			"title": "Koki Kru Topi jerami",
			"date":"7 April 2018",
			"path":"https://bangcodv.github.io/gambar/5.jpg"
		},

		{
			"title": "Portgas D Ace",
			"date":"8 April 2018",
			"path":"https://bangcodv.github.io/gambar/6.jpg"
		}

	]
}